numcaptcha.py
setup.py
numcaptcha.egg-info/PKG-INFO
numcaptcha.egg-info/SOURCES.txt
numcaptcha.egg-info/dependency_links.txt
numcaptcha.egg-info/top_level.txt
numcaptcha.egg-info/zip-safe
