Metadata-Version: 1.0
Name: numcaptcha
Version: 0.01
Summary: simple number captcha
Home-page: http://supreetsethi.net/drupal/
Author: Supreet Sethi
Author-email: supreet.sethi@gmail.com
License: UNKNOWN
Platform: UNKNOWN
Classifier: Development Status :: 4 - Beta
Classifier: Environment :: Console
Classifier: Intended Audience :: Developers
Classifier: Natural Language :: English
Classifier: License :: OSI Approved
Classifier: Operating System :: OS Independent
Classifier: Programming Language :: Python
Classifier: Topic :: Internet :: WWW/HTTP :: Dynamic Content
